Reg_Instrucciones.v
module Reg_Instrucciones (
    input wire clk,
    input wire rst,
    input wire update_flag,   // Pulso proveniente del Decodificador
    input wire [7:0] cmd_in,
    input wire [7:0] p1_in,
    input wire [7:0] p2_in,
    input wire [7:0] p3_in,
    
    // Los registros de estado persistentes
    output reg [7:0] reg_horas,
    output reg [7:0] reg_minutos,
    output reg [7:0] reg_segundos,
    output reg [3:0] reg_canales,
    output reg [3:0] reg_estados,
    output reg       reg_reset_sys,
    output reg       reg_iniciar
);

    always @(posedge clk or posedge rst) begin
        if (rst) begin
            // Estado inicial de la memoria al reiniciar la FPGA
            reg_horas     <= 8'd0;
            reg_minutos   <= 8'd0;
            reg_segundos  <= 8'd0;
            reg_canales   <= 4'b0000;
            reg_estados   <= 4'b0000;
            reg_reset_sys <= 1'b0;
            reg_iniciar   <= 1'b0;
        end else if (update_flag) begin
            // Solo actualizamos cuando la trama de 5 bytes es válida
            case (cmd_in)
                8'h48: begin // Letra 'H' - Configurar Hora
                    reg_horas    <= p1_in;
                    reg_minutos  <= p2_in;
                    reg_segundos <= p3_in;
                end
                
                8'h52: begin // Letra 'R' - Activar Reset Persistente
                    reg_reset_sys <= 1'b1;
                end
                
                8'h53: begin // Letra 'S' - Desactivar Reset (Set)
                    reg_reset_sys <= 1'b0;
                end
                
                8'h49: begin // Letra 'I' - Iniciar Reloj
                    reg_iniciar <= 1'b1;
                end
                
                8'h51: begin // Letra 'Q' - Activar un canal específico (1, 2, 3 o 4)
                    // Si recibimos 1, encendemos el bit 0. Si es 2, el bit 1, etc.
                    if (p1_in >= 8'd1 && p1_in <= 8'd4) begin
                        reg_canales[p1_in - 1] <= 1'b1;
                    end
                end
                
                8'h54: begin // Letra 'T' - Enviar datos a todos los canales
                    reg_canales <= 4'b1111;
                end
                
                8'h45: begin // Letra 'E' - Guardar estados
                    reg_estados <= p1_in[3:0]; // Tomamos solo los 4 bits bajos
                end
                
                default: begin
                    // Comando no reconocido, no hacemos nada
                end
            endcase
        end
    end
endmodule

Deco_Instrucciones.v
module Deco_Instrucciones (
    input  wire clk,
    input  wire rst,
    input  wire rx_valid,      // Indica que llegó un byte nuevo
    input  wire [7:0] rx_data, // El byte que llegó
    
    // Salidas hacia los registros
    output reg       update_flag,
    output reg [7:0] cmd_out,
    output reg [7:0] p1_out,
    output reg [7:0] p2_out,
    output reg [7:0] p3_out
);

    // Definición de los estados
    localparam ESPERAR_HEADER = 3'd0;
    localparam RECIBIR_CMD    = 3'd1;
    localparam RECIBIR_P1     = 3'd2;
    localparam RECIBIR_P2     = 3'd3;
    localparam RECIBIR_P3     = 3'd4;

    reg [2:0] estado_actual;

    always @(posedge clk or posedge rst) begin
        if (rst) begin
            estado_actual <= ESPERAR_HEADER;
            update_flag   <= 1'b0;
            cmd_out       <= 8'd0;
            p1_out        <= 8'd0;
            p2_out        <= 8'd0;
            p3_out        <= 8'd0;
        end else begin
            // Por defecto, la bandera de actualización dura solo 1 ciclo de reloj
            update_flag <= 1'b0;

            if (rx_valid) begin
                case (estado_actual)
                    ESPERAR_HEADER: begin
                        if (rx_data == 8'hAA) begin
                            estado_actual <= RECIBIR_CMD;
                        end
                    end
                    
                    RECIBIR_CMD: begin
                        cmd_out <= rx_data;
                        estado_actual <= RECIBIR_P1;
                    end
                    
                    RECIBIR_P1: begin
                        p1_out <= rx_data;
                        estado_actual <= RECIBIR_P2;
                    end
                    
                    RECIBIR_P2: begin
                        p2_out <= rx_data;
                        estado_actual <= RECIBIR_P3;
                    end
                    
                    RECIBIR_P3: begin
                        p3_out <= rx_data;
                        update_flag <= 1'b1; // ¡Trama completa! Avisar a memoria
                        estado_actual <= ESPERAR_HEADER; // Volver a empezar
                    end
                    
                    default: estado_actual <= ESPERAR_HEADER;
                endcase
            end
        end
    end
endmodule

UART_GC.v
module UART_Driver #(
    parameter N_BYTES  = 2,
    parameter CLK_FREC = 27000000,
    parameter BAUDRATE = 9600
)(
    input  clk, rst,
    input  pin_rx,
    output pin_tx,
    output [(N_BYTES*8)-1:0] rx_data,
    output                   rx_valid,
    input                    rx_ready,
    input  [(N_BYTES*8)-1:0] tx_data,
    input                    tx_valid,
    output                   tx_ready
);

    wire [7:0] u2b_data, b2u_data;
    wire u2b_valid, u2b_ready;
    wire b2u_valid, b2u_ready;

    UART_V1 #(
        .clk_frec_fpga(CLK_FREC), 
        .tasa_baudios(BAUDRATE)
    ) phy (
        .clk(clk), .rst(rst),
        .RX(pin_rx), .TX(pin_tx),
        .datos_recibido(u2b_data), .hecho_rx(u2b_valid), .next_ready(u2b_ready),
        .datos_enviar(b2u_data),   .datos_validos(b2u_valid), .tx_ready(b2u_ready),
        .hecho_tx()
    );

    UART_MultiByte_Bridge #(
        .N_BYTES(N_BYTES)
    ) bridge (
        .clk(clk), .rst(rst),
        .u_rx_data(u2b_data), .u_rx_valid(u2b_valid), .u_rx_ready(u2b_ready),
        .u_tx_data(b2u_data), .u_tx_valid(b2u_valid), .u_tx_ready(b2u_ready),
        .w_rx_data(rx_data), .w_rx_valid(rx_valid), .w_rx_ready(rx_ready),
        .w_tx_data(tx_data), .w_tx_valid(tx_valid), .w_tx_ready(tx_ready)
    );

endmodule

// ===============================================================================
// MODULO: UART_MultiByte_Bridge
// ===============================================================================
module UART_MultiByte_Bridge #(
    parameter N_BYTES = 2
)(
    input  clk, rst,
    input  [7:0] u_rx_data, input u_rx_valid, output reg u_rx_ready,
    output reg [7:0] u_tx_data, output reg u_tx_valid, input  u_tx_ready,
    output [(N_BYTES*8)-1:0] w_rx_data, output reg w_rx_valid, input w_rx_ready,
    input  [(N_BYTES*8)-1:0] w_tx_data, input  w_tx_valid, output reg w_tx_ready
);
    reg [7:0] rx_cnt; 
    reg [(N_BYTES*8)-1:0] rx_buf;

    assign w_rx_data = rx_buf;

    always @(posedge clk or posedge rst) begin
        if (rst) begin
            rx_cnt <= 8'd0; w_rx_valid <= 1'b0; u_rx_ready <= 1'b0;
        end else begin
            u_rx_ready <= 1'b1; 
            
            if (w_rx_valid && w_rx_ready) w_rx_valid <= 1'b0;

            if (u_rx_valid && u_rx_ready) begin
                rx_buf[rx_cnt*8 +: 8] <= u_rx_data;
                if (rx_cnt == N_BYTES - 1) begin
                    rx_cnt <= 8'd0;
                    w_rx_valid <= 1'b1;
                    u_rx_ready <= 1'b0;
                end else begin
                    rx_cnt <= rx_cnt + 8'd1;
                end
            end
        end
    end

    reg [7:0] tx_cnt;
    reg [(N_BYTES*8)-1:0] tx_buf;
    reg tx_active;

    always @(posedge clk or posedge rst) begin
        if (rst) begin
            tx_active <= 1'b0; tx_cnt <= 8'd0; u_tx_valid <= 1'b0; w_tx_ready <= 1'b0;
        end else begin
            if (!tx_active) begin
                u_tx_valid <= 1'b0; 
                tx_cnt <= 8'd0; 
                w_tx_ready <= 1'b1;

                if (w_tx_valid && w_tx_ready) begin
                    tx_buf <= w_tx_data;
                    w_tx_ready <= 1'b0;
                    tx_active <= 1'b1;
                end
            end else begin
                u_tx_data <= tx_buf[tx_cnt*8 +: 8];
                u_tx_valid <= 1'b1;

                if (u_tx_valid && u_tx_ready) begin
                    u_tx_valid <= 1'b0;
                    if (tx_cnt == N_BYTES - 1) begin
                        tx_active <= 1'b0;
                    end else begin
                        tx_cnt <= tx_cnt + 8'd1;
                    end
                end
            end
        end
    end
endmodule

// ===============================================================================
// MODULO: UART_V1
// ===============================================================================
module UART_V1 #(
    parameter clk_frec_fpga = 27000000,
    parameter tasa_baudios  = 9600
)(
    input  clk, rst,
    input  RX,
    input  [7:0] datos_enviar,
    input  datos_validos, 
    output [7:0] datos_recibido,
    output TX,
    output tx_ready,
    output hecho_rx,
    input  next_ready,
    output hecho_tx
);

    wire pulso;
    wire pulsox16;
    wire habilitar_gen;

    assign habilitar_gen = 1'b1; 

    UART_GenBaudio #(
        .clk_frec_fpga (clk_frec_fpga),
        .tasa_baudios  (tasa_baudios)
    ) GenBaudio1 (
        .clk      (clk),
        .rst      (rst),
        .habilitar(habilitar_gen),
        .pulso    (pulso),
        .pulsox16 (pulsox16)
    );

    UART_RX UART_RX1 (
        .clk            (clk),
        .rst            (rst),
        .pulsox16       (pulsox16),
        .RX             (RX),
        .next_ready     (next_ready),
        .datos_recibido (datos_recibido),
        .hecho_rx       (hecho_rx)
    );

    UART_TX UART_TX1 (
        .clk           (clk),
        .rst           (rst),
        .pulso         (pulso),
        .datos_validos (datos_validos),
        .datos_enviar  (datos_enviar),
        .TX            (TX),
        .tx_ready      (tx_ready),
        .hecho_tx      (hecho_tx)
    );

endmodule

// ===============================================================================
// MODULO: UART_GenBaudio
// ===============================================================================
module UART_GenBaudio #(
    parameter clk_frec_fpga = 27000000,
    parameter tasa_baudios = 9600
)(
    input clk,
    input rst,
    input habilitar,
    output reg pulso,
    output reg pulsox16
);

    localparam clk_contador = (clk_frec_fpga/(tasa_baudios*16));

    reg [15:0] contador;
    reg [3:0]  subcnt;

    always @(posedge clk or posedge rst) begin
        if (rst) begin
            contador <= 16'b0;
            subcnt   <= 4'b0;
            pulso    <= 1'b0;
            pulsox16 <= 1'b0;
        end 
        else if (habilitar) begin
            pulso    <= 1'b0;
            pulsox16 <= 1'b0;

            if (contador == clk_contador - 1) begin
                contador <= 16'b0;
                pulsox16 <= 1'b1;
                if (subcnt == 4'd15) begin
                    subcnt <= 4'b0;
                    pulso <= 1'b1;
                end
                else begin
                    subcnt <= subcnt + 4'b1;
                end 
            end 
            else begin
                contador <= contador + 16'b1;
            end
        end
        else begin
            contador <= 16'b0;
            subcnt   <= 4'b0;
            pulso    <= 1'b0;
            pulsox16 <= 1'b0;
        end 
    end

endmodule

// ===============================================================================
// MODULO: UART_RX
// ===============================================================================
module UART_RX (
    input  clk, rst,
    input  pulsox16,
    input  RX,
    input  next_ready,
    output reg [7:0] datos_recibido,
    output reg hecho_rx
);

    localparam IDLE       = 3'd0;
    localparam START      = 3'd1;
    localparam DATA       = 3'd2;
    localparam STOP       = 3'd3;
    localparam WAIT_READY = 3'd4;

    reg [2:0] estado;
    reg [2:0] contador_NroBit;
    reg [3:0] contador_pulsos;
    reg [7:0] shift_reg;
    reg rx_sync;
    reg rx_r;

    always @(posedge clk) begin
        rx_r    <= RX;
        rx_sync <= rx_r;
    end

    always @(posedge clk or posedge rst) begin
        if (rst) begin
            estado <= IDLE;
            contador_NroBit <= 3'd0;
            datos_recibido <= 8'b0;
            hecho_rx <= 1'b0;
            contador_pulsos <= 4'd0;
        end
        else begin
            case (estado)
                IDLE: begin
                    hecho_rx <= 1'b0;
                    contador_pulsos <= 4'd0;
                    contador_NroBit <= 3'd0;
                    if (rx_sync == 1'b0) begin 
                        estado <= START;
                    end
                end

                START: if (pulsox16) begin
                    if (contador_pulsos == 4'd7) begin
                        if (rx_sync == 1'b1) estado <= IDLE; 
                        else contador_pulsos <= contador_pulsos + 4'd1;
                    end
                    else if (contador_pulsos == 4'd15) begin
                        contador_pulsos <= 4'd0;
                        estado <= DATA;
                    end
                    else contador_pulsos <= contador_pulsos + 4'd1;
                end

                DATA: if (pulsox16) begin
                    if (contador_pulsos == 4'd7) begin
                        shift_reg[contador_NroBit] <= rx_sync;
                        contador_pulsos <= contador_pulsos + 4'd1;
                    end
                    else if (contador_pulsos == 4'd15) begin
                        contador_pulsos <= 4'd0;
                        if (contador_NroBit == 3'd7) estado <= STOP;
                        else contador_NroBit <= contador_NroBit + 3'd1;
                    end
                    else contador_pulsos <= contador_pulsos + 4'd1;
                end

                STOP: if (pulsox16) begin
                    if (contador_pulsos == 4'd7) begin
                        if (rx_sync == 1'b1) begin 
                            datos_recibido <= shift_reg;
                        end
                        contador_pulsos <= contador_pulsos + 4'd1;
                    end
                    else if (contador_pulsos == 4'd15) begin
                        contador_pulsos <= 4'd0;
                        hecho_rx <= 1'b1; 
                        estado <= WAIT_READY; 
                    end
                    else contador_pulsos <= contador_pulsos + 4'd1;
                end

                WAIT_READY: begin
                    if (next_ready) begin
                        hecho_rx <= 1'b0; 
                        estado <= IDLE;
                    end
                end
                default: estado <= IDLE;
            endcase
        end
    end
endmodule

// ===============================================================================
// MODULO: UART_TX
// ===============================================================================
module UART_TX (
    input  clk, rst,
    input  pulso,
    input  datos_validos,
    input  [7:0] datos_enviar,
    output reg TX,
    output tx_ready,
    output reg hecho_tx
);

    localparam IDLE  = 2'd0;
    localparam START = 2'd1;
    localparam DATA  = 2'd2;
    localparam STOP  = 2'd3;

    reg [1:0] estado;
    reg [2:0] contador_NroBit;
    reg [7:0] datosTX;

    assign tx_ready = (estado == IDLE);

    always @(posedge clk or posedge rst) begin
        if (rst) begin
            estado <= IDLE;
            contador_NroBit <= 3'd0;
            TX <= 1'b1;
            hecho_tx <= 1'b0;
        end
        else begin
            case (estado)
                IDLE: begin
                    hecho_tx <= 1'b0;
                    TX <= 1'b1;
                    if (datos_validos) begin
                        datosTX <= datos_enviar;
                        estado <= START;
                    end
                end

                START: if (pulso) begin
                    TX <= 1'b0; 
                    contador_NroBit <= 3'd0;
                    estado <= DATA;
                end

                DATA: if (pulso) begin
                    TX <= datosTX[contador_NroBit];
                    if (contador_NroBit == 3'd7)
                        estado <= STOP;
                    else
                        contador_NroBit <= contador_NroBit + 3'd1;
                end 

                STOP: if (pulso) begin
                    TX <= 1'b1;
                    hecho_tx <= 1'b1;
                    estado <= IDLE;
                end
                
                default: estado <= IDLE;
            endcase
        end
    end
endmodule

Receptor Instrucciones.v
module Receptor_Instrucciones #(
    // ¡Aquí cambias la frecuencia fácilmente!
    parameter FRECUENCIA_RELOJ = 27000000, 
    parameter BAUDRATE         = 9600
)(
    input  wire clk,
    input  wire rst,      // Botón de reset general del sistema
    input  wire pin_rx,   // Pin físico conectado al TX del Pi Pico/PC
    output wire pin_tx,   // Pin físico (opcional, por si luego quieres enviar datos)
    
    // ==========================================
    // SALIDAS CONTINUAS PARA TU COMPAÑERO
    // ==========================================
    output wire [7:0] out_horas,
    output wire [7:0] out_minutos,
    output wire [7:0] out_segundos,
    output wire [3:0] out_canales,
    output wire [3:0] out_estados,
    output wire       out_reset_sys,
    output wire       out_iniciar_reloj
);

    // Cables internos para conectar UART con Decodificador
    wire [7:0] uart_rx_data;
    wire       uart_rx_valid;
    wire       uart_rx_ready = 1'b1; // Siempre listos para recibir
    
    // Cables internos para conectar Decodificador con Registros
    wire       update_flag;
    wire [7:0] cmd_bus;
    wire [7:0] p1_bus, p2_bus, p3_bus;

    // 1. Instancia del UART (El módulo que tú me diste)
    UART_Driver #(
        .N_BYTES(1), 
        .CLK_FREC(FRECUENCIA_RELOJ),
        .BAUDRATE(BAUDRATE)
    ) mi_uart (
        .clk     (clk),
        .rst     (rst),
        .pin_rx  (pin_rx),
        .pin_tx  (pin_tx),
        .rx_data (uart_rx_data),
        .rx_valid(uart_rx_valid),
        .rx_ready(uart_rx_ready),
        .tx_data (8'd0),   // No transmitimos nada por ahora
        .tx_valid(1'b0),
        .tx_ready()
    );

    // 2. Instancia del Decodificador (El Parser)
    Deco_Instrucciones decodificador (
        .clk          (clk),
        .rst          (rst),
        .rx_valid     (uart_rx_valid),
        .rx_data      (uart_rx_data),
        .update_flag  (update_flag),
        .cmd_out      (cmd_bus),
        .p1_out       (p1_bus),
        .p2_out       (p2_bus),
        .p3_out       (p3_bus)
    );

    // 3. Instancia del Banco de Registros (La Memoria)
    Reg_Instrucciones registros (
        .clk          (clk),
        .rst          (rst),
        .update_flag  (update_flag),
        .cmd_in       (cmd_bus),
        .p1_in        (p1_bus),
        .p2_in        (p2_bus),
        .p3_in        (p3_bus),
        .reg_horas    (out_horas),
        .reg_minutos  (out_minutos),
        .reg_segundos (out_segundos),
        .reg_canales  (out_canales),
        .reg_estados  (out_estados),
        .reg_reset_sys(out_reset_sys),
        .reg_iniciar  (out_iniciar_reloj)
    );

endmodule

tb_Receptor_Instrucciones.v
`timescale 1ns/1ps

module tb_Receptor_Instrucciones();
    reg clk = 0;
    reg rst = 1;
    reg pin_rx = 1;
    
    // Salidas del Banco de Registros
    wire [7:0] h, m, s, canales, estados;
    wire rst_sys, init;

    // Instancia del sistema (Asegúrate de que el nombre del archivo coincida)
    Receptor_Instrucciones #(
        .FRECUENCIA_RELOJ(27000000),
        .BAUDRATE(115200) 
    ) uut (
        .clk(clk), .rst(rst), .pin_rx(pin_rx), .pin_tx(),
        .out_horas(h), .out_minutos(m), .out_segundos(s),
        .out_canales(canales), .out_estados(estados),
        .out_reset_sys(rst_sys), .out_iniciar_reloj(init)
    );

    // Reloj de 27MHz
    always #18.5 clk = ~clk;

    // Tarea para simular el envío UART (LSB first)
    task enviar_byte(input [7:0] dato);
        integer i;
        begin
            pin_rx = 0; // Bit de Inicio
            #(8680);    // Tiempo de bit para 115200 baudios
            for (i = 0; i < 8; i = i + 1) begin
                pin_rx = dato[i];
                #(8680);
            end
            pin_rx = 1; // Bit de Parada
            #(8680);
        end
    endtask

    initial begin
        $dumpfile("Receptor_Instrucciones.vcd");
        $dumpvars(0, tb_Receptor_Instrucciones);

        // Reset inicial del sistema
        #100 rst = 0; 
        #200;

        // --- INSTRUCCIÓN 1: CONFIGURAR HORA 08:30:15 ---
        // Paquete: AA 48 08 1E 0F
        enviar_byte(8'hAA); 
        enviar_byte(8'h48); // 'H'
        enviar_byte(8'h08); // 8 horas
        enviar_byte(8'h1E); // 30 minutos
        enviar_byte(8'h0F); // 15 segundos
        #20000; // Espera para observar estabilidad

        // --- INSTRUCCIÓN 2: ACTIVAR RESET DEL SISTEMA ---
        // Paquete: AA 52 00 00 00
        enviar_byte(8'hAA);
        enviar_byte(8'h52); // 'R'
        enviar_byte(8'h00);
        enviar_byte(8'h00);
        enviar_byte(8'h00);
        #20000;

        // --- INSTRUCCIÓN 3: ACTIVAR CANAL 3 ---
        // Paquete: AA 51 03 00 00
        enviar_byte(8'hAA);
        enviar_byte(8'h51); // 'Q'
        enviar_byte(8'h03); // Canal 3
        enviar_byte(8'h00);
        enviar_byte(8'h00);

        #50000;
        $display("Simulación finalizada.");
        $finish;
    end
endmodule

Receptor_Instrucciones.vcd
$date
	Sat Apr 18 02:34:51 2026
$end
$version
	Icarus Verilog
$end
$timescale
	1ps
$end
$scope module tb_Receptor_Instrucciones $end
$var wire 8 ! s [7:0] $end
$var wire 1 " rst_sys $end
$var wire 8 # m [7:0] $end
$var wire 1 $ init $end
$var wire 8 % h [7:0] $end
$var wire 8 & estados [7:0] $end
$var wire 8 ' canales [7:0] $end
$var reg 1 ( clk $end
$var reg 1 ) pin_rx $end
$var reg 1 * rst $end
$scope module uut $end
$var wire 1 ( clk $end
$var wire 1 ) pin_rx $end
$var wire 1 * rst $end
$var wire 1 + uart_rx_ready $end
$var wire 1 , update_flag $end
$var wire 1 - uart_rx_valid $end
$var wire 8 . uart_rx_data [7:0] $end
$var wire 1 / pin_tx $end
$var wire 8 0 p3_bus [7:0] $end
$var wire 8 1 p2_bus [7:0] $end
$var wire 8 2 p1_bus [7:0] $end
$var wire 8 3 out_segundos [7:0] $end
$var wire 1 " out_reset_sys $end
$var wire 8 4 out_minutos [7:0] $end
$var wire 1 $ out_iniciar_reloj $end
$var wire 8 5 out_horas [7:0] $end
$var wire 4 6 out_estados [3:0] $end
$var wire 4 7 out_canales [3:0] $end
$var wire 8 8 cmd_bus [7:0] $end
$var parameter 32 9 BAUDRATE $end
$var parameter 32 : FRECUENCIA_RELOJ $end
$scope module decodificador $end
$var wire 1 ( clk $end
$var wire 1 * rst $end
$var wire 1 - rx_valid $end
$var wire 8 ; rx_data [7:0] $end
$var parameter 3 < ESPERAR_HEADER $end
$var parameter 3 = RECIBIR_CMD $end
$var parameter 3 > RECIBIR_P1 $end
$var parameter 3 ? RECIBIR_P2 $end
$var parameter 3 @ RECIBIR_P3 $end
$var reg 8 A cmd_out [7:0] $end
$var reg 3 B estado_actual [2:0] $end
$var reg 8 C p1_out [7:0] $end
$var reg 8 D p2_out [7:0] $end
$var reg 8 E p3_out [7:0] $end
$var reg 1 , update_flag $end
$upscope $end
$scope module mi_uart $end
$var wire 1 ( clk $end
$var wire 1 ) pin_rx $end
$var wire 1 * rst $end
$var wire 1 + rx_ready $end
$var wire 8 F tx_data [7:0] $end
$var wire 1 G tx_valid $end
$var wire 1 H u2b_valid $end
$var wire 1 I u2b_ready $end
$var wire 8 J u2b_data [7:0] $end
$var wire 1 K tx_ready $end
$var wire 1 - rx_valid $end
$var wire 8 L rx_data [7:0] $end
$var wire 1 / pin_tx $end
$var wire 1 M b2u_valid $end
$var wire 1 N b2u_ready $end
$var wire 8 O b2u_data [7:0] $end
$var parameter 32 P BAUDRATE $end
$var parameter 32 Q CLK_FREC $end
$var parameter 32 R N_BYTES $end
$scope module bridge $end
$var wire 1 ( clk $end
$var wire 1 * rst $end
$var wire 8 S w_rx_data [7:0] $end
$var wire 1 + w_rx_ready $end
$var wire 8 T w_tx_data [7:0] $end
$var wire 1 G w_tx_valid $end
$var wire 1 N u_tx_ready $end
$var wire 1 H u_rx_valid $end
$var wire 8 U u_rx_data [7:0] $end
$var parameter 32 V N_BYTES $end
$var reg 8 W rx_buf [7:0] $end
$var reg 8 X rx_cnt [7:0] $end
$var reg 1 Y tx_active $end
$var reg 8 Z tx_buf [7:0] $end
$var reg 8 [ tx_cnt [7:0] $end
$var reg 1 I u_rx_ready $end
$var reg 8 \ u_tx_data [7:0] $end
$var reg 1 M u_tx_valid $end
$var reg 1 - w_rx_valid $end
$var reg 1 K w_tx_ready $end
$upscope $end
$scope module phy $end
$var wire 1 ) RX $end
$var wire 1 ( clk $end
$var wire 8 ] datos_enviar [7:0] $end
$var wire 1 M datos_validos $end
$var wire 1 ^ habilitar_gen $end
$var wire 1 I next_ready $end
$var wire 1 * rst $end
$var wire 1 N tx_ready $end
$var wire 1 _ pulsox16 $end
$var wire 1 ` pulso $end
$var wire 1 a hecho_tx $end
$var wire 1 H hecho_rx $end
$var wire 8 b datos_recibido [7:0] $end
$var wire 1 / TX $end
$var parameter 32 c clk_frec_fpga $end
$var parameter 32 d tasa_baudios $end
$scope module GenBaudio1 $end
$var wire 1 ( clk $end
$var wire 1 ^ habilitar $end
$var wire 1 * rst $end
$var parameter 64 e clk_contador $end
$var parameter 32 f clk_frec_fpga $end
$var parameter 32 g tasa_baudios $end
$var reg 16 h contador [15:0] $end
$var reg 1 ` pulso $end
$var reg 1 _ pulsox16 $end
$var reg 4 i subcnt [3:0] $end
$upscope $end
$scope module UART_RX1 $end
$var wire 1 ) RX $end
$var wire 1 ( clk $end
$var wire 1 I next_ready $end
$var wire 1 _ pulsox16 $end
$var wire 1 * rst $end
$var parameter 3 j DATA $end
$var parameter 3 k IDLE $end
$var parameter 3 l START $end
$var parameter 3 m STOP $end
$var parameter 3 n WAIT_READY $end
$var reg 3 o contador_NroBit [2:0] $end
$var reg 4 p contador_pulsos [3:0] $end
$var reg 8 q datos_recibido [7:0] $end
$var reg 3 r estado [2:0] $end
$var reg 1 H hecho_rx $end
$var reg 1 s rx_r $end
$var reg 1 t rx_sync $end
$var reg 8 u shift_reg [7:0] $end
$upscope $end
$scope module UART_TX1 $end
$var wire 1 ( clk $end
$var wire 8 v datos_enviar [7:0] $end
$var wire 1 M datos_validos $end
$var wire 1 ` pulso $end
$var wire 1 * rst $end
$var wire 1 N tx_ready $end
$var parameter 2 w DATA $end
$var parameter 2 x IDLE $end
$var parameter 2 y START $end
$var parameter 2 z STOP $end
$var reg 1 / TX $end
$var reg 3 { contador_NroBit [2:0] $end
$var reg 8 | datosTX [7:0] $end
$var reg 2 } estado [1:0] $end
$var reg 1 a hecho_tx $end
$upscope $end
$upscope $end
$upscope $end
$scope module registros $end
$var wire 1 ( clk $end
$var wire 8 ~ cmd_in [7:0] $end
$var wire 8 !" p1_in [7:0] $end
$var wire 8 "" p2_in [7:0] $end
$var wire 8 #" p3_in [7:0] $end
$var wire 1 * rst $end
$var wire 1 , update_flag $end
$var reg 4 $" reg_canales [3:0] $end
$var reg 4 %" reg_estados [3:0] $end
$var reg 8 &" reg_horas [7:0] $end
$var reg 1 $ reg_iniciar $end
$var reg 8 '" reg_minutos [7:0] $end
$var reg 1 " reg_reset_sys $end
$var reg 8 (" reg_segundos [7:0] $end
$upscope $end
$upscope $end
$scope task enviar_byte $end
$var reg 8 )" dato [7:0] $end
$var integer 32 *" i [31:0] $end
$upscope $end
$upscope $end
$enddefinitions $end
$comment Show the parameter values. $end
$dumpall
b11 z
b1 y
b0 x
b10 w
b100 n
b11 m
b1 l
b0 k
b10 j
b11100001000000000 g
b1100110111111110011000000 f
b1110 e
b11100001000000000 d
b1100110111111110011000000 c
b1 V
b1 R
b1100110111111110011000000 Q
b11100001000000000 P
b100 @
b11 ?
b10 >
b1 =
b0 <
b1100110111111110011000000 :
b11100001000000000 9
$end
#0
$dumpvars
bx *"
bx )"
b0 ("
b0 '"
b0 &"
b0 %"
b0 $"
b0 #"
b0 ""
b0 !"
b0 ~
b0 }
bx |
b0 {
bx v
bx u
xt
xs
b0 r
b0 q
b0 p
b0 o
b0 i
b0 h
b0 b
0a
0`
0_
1^
bx ]
bx \
b0 [
bx Z
0Y
b0 X
bx W
b0 U
b0 T
bx S
bx O
1N
0M
bx L
0K
b0 J
0I
0H
0G
b0 F
b0 E
b0 D
b0 C
b0 B
b0 A
bx ;
b0 8
b0 7
b0 6
b0 5
b0 4
b0 3
b0 2
b0 1
b0 0
1/
bx .
0-
0,
1+
1*
1)
0(
b0 '
b0 &
b0 %
0$
b0 #
0"
b0 !
$end
#18500
1s
1(
#37000
0(
#55500
1t
1(
#74000
0(
#92500
1(
#100000
0*
#111000
0(
#129500
b1 h
1I
1K
1(
#148000
0(
#166500
b10 h
1(
#185000
0(
#203500
b11 h
1(
#222000
0(
#240500
b100 h
1(
#259000
0(
#277500
b101 h
1(
#296000
0(
#300000
0)
b10101010 )"
#314500
b110 h
0s
1(
#333000
0(
#351500
b111 h
0t
1(
#370000
0(
#388500
b1 r
b1000 h
1(
#407000
0(
#425500
b1001 h
1(
#444000
0(
#462500
b1010 h
1(
#481000
0(
#499500
b1011 h
1(
#518000
0(
#536500
b1100 h
1(
#555000
0(
#573500
b1101 h
1(
#592000
0(
#610500
b1 i
1_
b0 h
1(
#629000
0(
#647500
b1 h
0_
b1 p
1(
#666000
0(
#684500
b10 h
1(
#703000
0(
#721500
b11 h
1(
#740000
0(
#758500
b100 h
1(
#777000
0(
#795500
b101 h
1(
#814000
0(
#832500
b110 h
1(
#851000
0(
#869500
b111 h
1(
#888000
0(
#906500
b1000 h
1(
#925000
0(
#943500
b1001 h
1(
#962000
0(
#980500
b1010 h
1(
#999000
0(
#1017500
b1011 h
1(
#1036000
0(
#1054500
b1100 h
1(
#1073000
0(
#1091500
b1101 h
1(
#1110000
0(
#1128500
b10 i
1_
b0 h
1(
#1147000
0(
#1165500
b1 h
0_
b10 p
1(
#1184000
0(
#1202500
b10 h
1(
#1221000
0(
#1239500
b11 h
1(
#1258000
0(
#1276500
b100 h
1(
#1295000
0(
#1313500
b101 h
1(
#1332000
0(
#1350500
b110 h
1(
#1369000
0(
#1387500
b111 h
1(
#1406000
0(
#1424500
b1000 h
1(
#1443000
0(
#1461500
b1001 h
1(
#1480000
0(
#1498500
b1010 h
1(
#1517000
0(
#1535500
b1011 h
1(
#1554000
0(
#1572500
b1100 h
1(
#1591000
0(
#1609500
b1101 h
1(
#1628000
0(
#1646500
b11 i
1_
b0 h
1(
#1665000
0(
#1683500
b1 h
0_
b11 p
1(
#1702000
0(
#1720500
b10 h
1(
#1739000
0(
#1757500
b11 h
1(
#1776000
0(
#1794500
b100 h
1(
#1813000
0(
#1831500
b101 h
1(
#1850000
0(
#1868500
b110 h
1(
#1887000
0(
#1905500
b111 h
1(
#1924000
0(
#1942500
b1000 h
1(
#1961000
0(
#1979500
b1001 h
1(
#1998000
0(
#2016500
b1010 h
1(
#2035000
0(
#2053500
b1011 h
1(
#2072000
0(
#2090500
b1100 h
1(
#2109000
0(
#2127500
b1101 h
1(
#2146000
0(
#2164500
b100 i
1_
b0 h
1(
#2183000
0(
#2201500
b1 h
0_
b100 p
1(
#2220000
0(
#2238500
b10 h
1(
#2257000
0(
#2275500
b11 h
1(
#2294000
0(
#2312500
b100 h
1(
#2331000
0(
#2349500
b101 h
1(
#2368000
0(
#2386500
b110 h
1(
#2405000
0(
#2423500
b111 h
1(
#2442000
0(
#2460500
b1000 h
1(
#2479000
0(
#2497500
b1001 h
1(
#2516000
0(
#2534500
b1010 h
1(
#2553000
0(
#2571500
b1011 h
1(
#2590000
0(
#2608500
b1100 h
1(
#2627000
0(
#2645500
b1101 h
1(
#2664000
0(
#2682500
b101 i
1_
b0 h
1(
#2701000
0(
#2719500
b1 h
0_
b101 p
1(
#2738000
0(
#2756500
b10 h
1(
#2775000
0(
#2793500
b11 h
1(
#2812000
0(
#2830500
b100 h
1(
#2849000
0(
#2867500
b101 h
1(
#2886000
0(
#2904500
b110 h
1(
#2923000
0(
#2941500
b111 h
1(
#2960000
0(
#2978500
b1000 h
1(
#2997000
0(
#3015500
b1001 h
1(
#3034000
0(
#3052500
b1010 h
1(
#3071000
0(
#3089500
b1011 h
1(
#3108000
0(
#3126500
b1100 h
1(
#3145000
0(
#3163500
b1101 h
1(
#3182000
0(
#3200500
b110 i
1_
b0 h
1(
#3219000
0(
#3237500
b1 h
0_
b110 p
1(
#3256000
0(
#3274500
b10 h
1(
#3293000
0(
#3311500
b11 h
1(
#3330000
0(
#3348500
b100 h
1(
#3367000
0(
#3385500
b101 h
1(
#3404000
0(
#3422500
b110 h
1(
#3441000
0(
#3459500
b111 h
1(
#3478000
0(
#3496500
b1000 h
1(
#3515000
0(
#3533500
b1001 h
1(
#3552000
0(
#3570500
b1010 h
1(
